skore/__init__.py
skore/authentication_service.py
skore/integration_service.py
skore/recommendation_service.py
skore/skore_knowledge_service.py
skore/meya/__init__.py
skore/meya/issue_tracker.py
skore/meya/user.py
skore_chatbot_sdk-0.0.6.dist-info/DESCRIPTION.rst
skore_chatbot_sdk-0.0.6.dist-info/METADATA
skore_chatbot_sdk-0.0.6.dist-info/RECORD
skore_chatbot_sdk-0.0.6.dist-info/WHEEL
skore_chatbot_sdk-0.0.6.dist-info/metadata.json
skore_chatbot_sdk-0.0.6.dist-info/top_level.txt
