Metadata-Version: 2.0
Name: skore-chatbot-sdk
Version: 0.0.6
Summary: Include common chatbot functionality.
Home-page: https://github.com/skore-io/skore-chatbot-sdk
Author: skore.io
Author-email: support@skore.io
License: None
Platform: UNKNOWN
Requires-Dist: requests
